ctsf/__init__.py
ctsf/ctsf.py
ctsf/core/__init__.py
ctsf/core/handler.py
ctsf/core/runner.py
ctsf/modules/__init__.py
ctsf/modules/request.py
ctsf/modules/who.py
ctsf-1.0.6.dist-info/LICENSE
ctsf-1.0.6.dist-info/METADATA
ctsf-1.0.6.dist-info/WHEEL
ctsf-1.0.6.dist-info/entry_points.txt
ctsf-1.0.6.dist-info/top_level.txt
ctsf-1.0.6.dist-info/RECORD
