Metadata-Version: 2.1
Name: ctsf
Version: 1.0.6
Summary: Certificate Transparency Subdomain Finder + WHOIS Data
Home-page: https://github.com/erfansamandarian/ctsf
Author: Erfan Samandarian
Author-email: mail@erfansamandarian.com
License: MIT
License-File: LICENSE
Requires-Dist: requests
Requires-Dist: python-whois
Requires-Dist: tabulate
Requires-Dist: termcolor
